taskiq_faststream/__about__.py
taskiq_faststream/__init__.py
taskiq_faststream/broker.py
taskiq_faststream/formatter.py
taskiq_faststream/kicker.py
taskiq_faststream/py.typed
taskiq_faststream/scheduler.py
taskiq_faststream/types.py
taskiq_faststream/utils.py
taskiq_faststream-0.4.0.dist-info/licenses/LICENSE
taskiq_faststream-0.4.0.dist-info/WHEEL
taskiq_faststream-0.4.0.dist-info/METADATA
taskiq_faststream-0.4.0.dist-info/RECORD
