Metadata-Version: 2.4
Name: taskiq-faststream
Version: 0.4.0
Summary: FastStream - taskiq integration to schedule FastStream tasks
Keywords: taskiq,tasks,distributed,async,FastStream
Author: Taskiq team, Nikita Pastukhov
Author-email: Taskiq team <taskiq@no-reply.com>, Nikita Pastukhov <nikita@pastukhov-dev.ru>
License-Expression: MIT
License-File: LICENSE
Classifier: Development Status :: 5 - Production/Stable
Classifier: License :: OSI Approved :: MIT License
Classifier: Programming Language :: Python
Classifier: Programming Language :: Python :: 3
Classifier: Programming Language :: Python :: 3 :: Only
Classifier: Programming Language :: Python :: 3.10
Classifier: Programming Language :: Python :: 3.11
Classifier: Programming Language :: Python :: 3.12
Classifier: Programming Language :: Python :: 3.13
Classifier: Programming Language :: Python :: 3.14
Classifier: Operating System :: OS Independent
Classifier: Topic :: Software Development :: Libraries :: Python Modules
Classifier: Topic :: Software Development :: Libraries
Classifier: Topic :: Software Development
Classifier: Topic :: System :: Networking
Classifier: Typing :: Typed
Classifier: Intended Audience :: Developers
Classifier: Intended Audience :: Information Technology
Classifier: Framework :: Pydantic
Classifier: Framework :: Pydantic :: 1
Classifier: Framework :: Pydantic :: 2
Requires-Dist: taskiq>=0.12.1,<0.13.0
Requires-Dist: faststream>=0.3.14,<0.7
Requires-Dist: faststream[confluent] ; extra == 'confluent'
Requires-Dist: faststream[kafka] ; extra == 'kafka'
Requires-Dist: faststream[nats] ; extra == 'nats'
Requires-Dist: taskiq[opentelemetry] ; extra == 'otel'
Requires-Dist: faststream[rabbit] ; extra == 'rabbit'
Requires-Dist: faststream[redis] ; extra == 'redis'
Requires-Python: >=3.10
Project-URL: Homepage, https://github.com/taskiq-python/taskiq-faststream
Project-URL: Source, https://github.com/taskiq-python/taskiq-faststream
Project-URL: Tracker, https://github.com/taskiq-python/taskiq-faststream/issues
Provides-Extra: confluent
Provides-Extra: kafka
Provides-Extra: nats
Provides-Extra: otel
Provides-Extra: rabbit
Provides-Extra: redis
